pyclsload/__init__.py
pyclsload/__main__.py
pyclsload-1.6.0.dist-info/METADATA
pyclsload-1.6.0.dist-info/WHEEL
pyclsload-1.6.0.dist-info/licenses/LICENSE
pyclsload-1.6.0.dist-info/RECORD
