Metadata-Version: 2.4
Name: pyclsload
Version: 1.6.0
Project-URL: Homepage, https://github.com/nbdy/pyclsload
Project-URL: Repository, https://github.com/nbdy/pyclsload.git
Project-URL: Issues, https://github.com/nbdy/pyclsload/issues
Author: nbdy
Maintainer: nbdy
License: MIT License
License-File: LICENSE
Classifier: Development Status :: 4 - Beta
Classifier: License :: OSI Approved :: MIT License
Classifier: Programming Language :: Python :: 3.11
Classifier: Programming Language :: Python :: 3.12
Requires-Python: >=3.8
